{"VNGFep6rncY": {"depth": 8, "recommendations": []}, "vuIlsN32WaE": {"depth": 8, "recommendations": []}, "9wjjQ55S4Nc": {"depth": 6, "recommendations": ["waeMkka60po", "Ie6zd3Rwu4c"]}, "td9qhhOJp2U": {"depth": 8, "recommendations": []}, "KLKNOCazJRs": {"depth": 6, "recommendations": ["aeM2G_p4hFo", "fCPSZaeAulI"]}, "jz_CyZy1akM": {"depth": 6, "recommendations": ["kd2Mei-SihI"]}, "9b1iDMW0y7s": {"depth": 6, "recommendations": ["R6aImfx8Iic", "vsZ8ageOkzo"]}, "xnnmcP6FkWk": {"depth": 4, "recommendations": ["aeM2G_p4hFo", "wjrOaYcSFlI"]}, "8w0iUOz-ofU": {"depth": 7, "recommendations": ["hx2Sh4aPriI", "tQyJlKI26lk"]}, "yUidpjr8Xzw": {"depth": 5, "recommendations": ["GrIFD16M4S0", "l9nlrSgmhQo"]}, "uf7hQAB6drQ": {"depth": 4, "recommendations": ["3iFjNFRnaqg", "9QPTUFcGHoA"]}, "PLpCQLU0-Xc": {"depth": 8, "recommendations": []}, "QiI9hR5jezQ": {"depth": 8, "recommendations": []}, "twG4mr6Jov0": {"depth": 7, "recommendations": ["v_ONFix_e4k", "f0WCb23KPEw"]}, "qALz88lgdUI": {"depth": 4, "recommendations": ["96wAdlnyUCg", "h1XVLCsvNFg"]}, "QRsCXUkTJyM": {"depth": 6, "recommendations": ["8w0iUOz-ofU", "4PV1xl6mq98"]}, "pxCLtwec71M": {"depth": 7, "recommendations": ["zsxZfz83Jjo", "QRnDXBuslk4"]}, "tQyJlKI26lk": {"depth": 8, "recommendations": []}, "X1qebkWD67o": {"depth": 4, "recommendations": ["5MCdlgPZFJ4", "Gs4ECUBdeM0"]}, "f5rUPatnXSE": {"depth": 7, "recommendations": ["3wj48ACMWeI", "kasiov0ytEc"]}, "OpapdB-bCFI": {"depth": 8, "recommendations": []}, "U-XnWz0WmE8": {"depth": 8, "recommendations": []}, "waeMkka60po": {"depth": 7, "recommendations": ["9wjjQ55S4Nc", "QXUdozfL7iM"]}, "ixhYVcWwJiY": {"depth": 6, "recommendations": ["hUbpaVrBGFM", "NIkGBYZPDiU"]}, "tbTP1s28hqs": {"depth": 8, "recommendations": []}, "qGO7HVckD0A": {"depth": 8, "recommendations": []}, "viWM1l_U4Pc": {"depth": 8, "recommendations": []}, "iCpKUvYnnn4": {"depth": 0, "recommendations": ["e8ZwxNKBtRQ", "jENapQxK6bc"]}, "-b2flEOjgjE": {"depth": 4, "recommendations": ["VCWtzfcmcfc", "3EnJvYGjI38"]}, "zsxZfz83Jjo": {"depth": 6, "recommendations": ["pxCLtwec71M"]}, "kvqjXxDDxOE": {"depth": 8, "recommendations": []}, "JlthbJTv39U": {"depth": 8, "recommendations": []}, "R6aImfx8Iic": {"depth": 7, "recommendations": ["-TFQjYfrE0Q", "l9nlrSgmhQo"]}, "pBbvehbomrY": {"depth": 6, "recommendations": ["jMoOu0L9Y64", "m0sY2tjmr_Y"]}, "xSz6riPcbYU": {"depth": 8, "recommendations": []}, "OvYzUWUh2xE": {"depth": 5, "recommendations": ["A1Gu36jWZtE", "9wjjQ55S4Nc"]}, "hUbpaVrBGFM": {"depth": 7, "recommendations": ["viWM1l_U4Pc", "xSz6riPcbYU"]}, "kU6i_HEKJgg": {"depth": 8, "recommendations": []}, "6M6zK017XRU": {"depth": 8, "recommendations": []}, "96wAdlnyUCg": {"depth": 5, "recommendations": ["qALz88lgdUI", "tkIg-SxPzTA"]}, "Y6rX9Gn0a00": {"depth": 4, "recommendations": ["MzuwbdIjcvs", "usLCNC23Los"]}, "jENapQxK6bc": {"depth": 1, "recommendations": ["Gs4ECUBdeM0"]}, "SSH5EY-W5oM": {"depth": 8, "recommendations": []}, "Gs4ECUBdeM0": {"depth": 2, "recommendations": ["VckmK-ZCpAU", "5MCdlgPZFJ4"]}, "VCWtzfcmcfc": {"depth": 5, "recommendations": ["-b2flEOjgjE", "N-yALPEpV4w"]}, "fmwUYrDooDQ": {"depth": 8, "recommendations": []}, "UMhLBPPtlrY": {"depth": 7, "recommendations": ["nhzV-J1h0do", "_fqpD3v_aOQ"]}, "tC_g4lgYN7Y": {"depth": 2, "recommendations": ["UY04N-WlSdQ", "jENapQxK6bc"]}, "KjC9kt7Qc_E": {"depth": 7, "recommendations": ["qGO7HVckD0A", "kvqjXxDDxOE"]}, "Rys45B4OhV0": {"depth": 7, "recommendations": ["f5rUPatnXSE", "I33E4yBoJvY"]}, "vez69nFr4u0": {"depth": 4, "recommendations": ["qB71WHEHEz8", "yUidpjr8Xzw"]}, "hx2Sh4aPriI": {"depth": 8, "recommendations": []}, "8UVUnUnWfHI": {"depth": 5, "recommendations": ["I33E4yBoJvY", "pBbvehbomrY"]}, "3EnJvYGjI38": {"depth": 4, "recommendations": ["UGoHALrUarY", "8UVUnUnWfHI"]}, "wPBWac-JFls": {"depth": 8, "recommendations": []}, "I33E4yBoJvY": {"depth": 6, "recommendations": ["f5rUPatnXSE", "Rys45B4OhV0"]}, "E0W1ZZYIV8o": {"depth": 8, "recommendations": []}, "zPeNkqa0_DE": {"depth": 8, "recommendations": []}, "MzuwbdIjcvs": {"depth": 3, "recommendations": ["A1Gu36jWZtE", "3EnJvYGjI38"]}, "wjrOaYcSFlI": {"depth": 5, "recommendations": ["PpuDYgibL_A", "jz_CyZy1akM"]}, "viDnOz12BFM": {"depth": 7, "recommendations": ["4PV1xl6mq98", "U-XnWz0WmE8"]}, "N-yALPEpV4w": {"depth": 6, "recommendations": ["kybenSq0KPo", "_mgDW_U1prQ"]}, "tkIg-SxPzTA": {"depth": 6, "recommendations": ["twG4mr6Jov0", "UMhLBPPtlrY"]}, "9QPTUFcGHoA": {"depth": 5, "recommendations": ["QRsCXUkTJyM", "5MCdlgPZFJ4"]}, "T7pwFxQqOxQ": {"depth": 8, "recommendations": []}, "qB71WHEHEz8": {"depth": 5, "recommendations": ["xN7jvtpxnZ0", "vez69nFr4u0"]}, "l9nlrSgmhQo": {"depth": 6, "recommendations": []}, "hEiU-8gx0hc": {"depth": 7, "recommendations": ["wjrOaYcSFlI", "OpapdB-bCFI"]}, "jMoOu0L9Y64": {"depth": 7, "recommendations": ["UZMIbo_DxJk", "T7pwFxQqOxQ"]}, "UY04N-WlSdQ": {"depth": 3, "recommendations": ["qALz88lgdUI", "vez69nFr4u0"]}, "fA5sGtj7QKQ": {"depth": 8, "recommendations": []}, "s9pLrLPBUeA": {"depth": 2, "recommendations": ["MzuwbdIjcvs", "WDdSsA9ZcrQ"]}, "2etvpGmo3KE": {"depth": 8, "recommendations": []}, "usLCNC23Los": {"depth": 5, "recommendations": ["Y6rX9Gn0a00", "ixhYVcWwJiY"]}, "VckmK-ZCpAU": {"depth": 3, "recommendations": ["Gs4ECUBdeM0", "xnnmcP6FkWk"]}, "zym75LrGRYo": {"depth": 8, "recommendations": []}, "WDdSsA9ZcrQ": {"depth": 3, "recommendations": ["-b2flEOjgjE", "Y6rX9Gn0a00"]}, "_fqpD3v_aOQ": {"depth": 8, "recommendations": []}, "A1Gu36jWZtE": {"depth": 4, "recommendations": ["MzuwbdIjcvs", "OvYzUWUh2xE"]}, "m0sY2tjmr_Y": {"depth": 7, "recommendations": ["fA5sGtj7QKQ", "E0W1ZZYIV8o"]}, "4PV1xl6mq98": {"depth": 8, "recommendations": []}, "kd2Mei-SihI": {"depth": 7, "recommendations": ["wPBWac-JFls"]}, "Ie6zd3Rwu4c": {"depth": 7, "recommendations": ["AGl3HxEMJhI", "ckipNktu28g"]}, "tHO1ebNxhVI": {"depth": 8, "recommendations": []}, "UGoHALrUarY": {"depth": 5, "recommendations": ["lteyAM7609I", "Y6rX9Gn0a00"]}, "QRnDXBuslk4": {"depth": 8, "recommendations": []}, "xN7jvtpxnZ0": {"depth": 6, "recommendations": ["-YFgydceacM", "l9nlrSgmhQo"]}, "fCPSZaeAulI": {"depth": 7, "recommendations": ["JlthbJTv39U", "kU6i_HEKJgg"]}, "v_ONFix_e4k": {"depth": 8, "recommendations": []}, "h1XVLCsvNFg": {"depth": 5, "recommendations": ["9b1iDMW0y7s", "l9nlrSgmhQo"]}, "_mgDW_U1prQ": {"depth": 7, "recommendations": ["VNGFep6rncY", "SSH5EY-W5oM"]}, "wexLhuDLZGw": {"depth": 8, "recommendations": []}, "vsZ8ageOkzo": {"depth": 7, "recommendations": ["2etvpGmo3KE", "td9qhhOJp2U"]}, "AGl3HxEMJhI": {"depth": 8, "recommendations": []}, "kybenSq0KPo": {"depth": 7, "recommendations": ["tHO1ebNxhVI", "vuIlsN32WaE"]}, "e8ZwxNKBtRQ": {"depth": 1, "recommendations": ["tC_g4lgYN7Y", "s9pLrLPBUeA"]}, "NIkGBYZPDiU": {"depth": 7, "recommendations": ["fmwUYrDooDQ", "wexLhuDLZGw"]}, "kasiov0ytEc": {"depth": 8, "recommendations": []}, "UZMIbo_DxJk": {"depth": 8, "recommendations": []}, "-YFgydceacM": {"depth": 7, "recommendations": ["tbTP1s28hqs", "PLpCQLU0-Xc"]}, "nhzV-J1h0do": {"depth": 8, "recommendations": []}, "aeM2G_p4hFo": {"depth": 5, "recommendations": ["KLKNOCazJRs", "xnnmcP6FkWk"]}, "HYFPGYljeOk": {"depth": 6, "recommendations": ["viDnOz12BFM", "xOhhxP0EFlA"]}, "5MCdlgPZFJ4": {"depth": 3, "recommendations": ["uf7hQAB6drQ", "X1qebkWD67o"]}, "xOhhxP0EFlA": {"depth": 7, "recommendations": ["zym75LrGRYo", "HYFPGYljeOk"]}, "ckipNktu28g": {"depth": 8, "recommendations": []}, "PpuDYgibL_A": {"depth": 6, "recommendations": ["wjrOaYcSFlI", "hEiU-8gx0hc"]}, "3iFjNFRnaqg": {"depth": 5, "recommendations": ["HYFPGYljeOk", "zsxZfz83Jjo"]}, "-TFQjYfrE0Q": {"depth": 8, "recommendations": []}, "f0WCb23KPEw": {"depth": 8, "recommendations": []}, "3wj48ACMWeI": {"depth": 8, "recommendations": []}, "GrIFD16M4S0": {"depth": 6, "recommendations": ["R0elzq3Ciec", "yUidpjr8Xzw"]}, "QXUdozfL7iM": {"depth": 8, "recommendations": []}, "R0elzq3Ciec": {"depth": 7, "recommendations": ["QiI9hR5jezQ", "6M6zK017XRU"]}, "lteyAM7609I": {"depth": 6, "recommendations": ["KjC9kt7Qc_E", "hKIqHKYAR04"]}, "hKIqHKYAR04": {"depth": 7, "recommendations": ["zPeNkqa0_DE", "kvqjXxDDxOE"]}}