{"lRRYLlXHkGs": {"depth": 8, "recommendations": []}, "d4yJAF0WDdk": {"depth": 6, "recommendations": ["U-XnWz0WmE8"]}, "8vW6qokJ22o": {"depth": 5, "recommendations": ["ZYezDwDURjM", "WnnzDYk02hk"]}, "xIUhGcBJ0b0": {"depth": 8, "recommendations": []}, "gGxdvkoYqrc": {"depth": 5, "recommendations": ["d4yJAF0WDdk"]}, "ZZninNuU90c": {"depth": 3, "recommendations": ["Envmqb9GZlY", "bah4WFDqKbQ"]}, "jENapQxK6bc": {"depth": 1, "recommendations": ["qofdWFv7m0U"]}, "uUm1hzcZkfI": {"depth": 8, "recommendations": []}, "jkMLVBHSBvA": {"depth": 4, "recommendations": ["K256zYBqugg", "8vW6qokJ22o"]}, "WnnzDYk02hk": {"depth": 7, "recommendations": ["ZYezDwDURjM", "dx2J5pWSeLA"]}, "8w0iUOz-ofU": {"depth": 3, "recommendations": ["hx2Sh4aPriI", "hHhYLJMi7CE"]}, "SLI-X8amRLU": {"depth": 7, "recommendations": ["q2l1XluxCMc", "9812fECnzAo"]}, "YQrMGlIE79M": {"depth": 6, "recommendations": ["K256zYBqugg", "t2ztuFzSiDY"]}, "b4ifJ1UZCfs": {"depth": 8, "recommendations": []}, "hx2Sh4aPriI": {"depth": 4, "recommendations": ["8w0iUOz-ofU", "hHhYLJMi7CE"]}, "9812fECnzAo": {"depth": 7, "recommendations": ["ZYezDwDURjM", "xIUhGcBJ0b0"]}, "id5b0PYgvwo": {"depth": 3, "recommendations": ["42wJQTZpBDE", "hHhYLJMi7CE"]}, "hHhYLJMi7CE": {"depth": 2, "recommendations": ["00jwuAz_vuA"]}, "00jwuAz_vuA": {"depth": 3, "recommendations": ["4s7Exvtz61I", "hHhYLJMi7CE"]}, "ZkFUU-xJM6I": {"depth": 1, "recommendations": ["rQ9X2I3X6UQ", "hHhYLJMi7CE"]}, "K256zYBqugg": {"depth": 5, "recommendations": ["YQrMGlIE79M"]}, "q2l1XluxCMc": {"depth": 8, "recommendations": []}, "42wJQTZpBDE": {"depth": 4, "recommendations": ["gGxdvkoYqrc", "hHhYLJMi7CE"]}, "5WD4zpt43TU": {"depth": 0, "recommendations": ["ZkFUU-xJM6I", "jENapQxK6bc"]}, "4s7Exvtz61I": {"depth": 4, "recommendations": ["00jwuAz_vuA", "hHhYLJMi7CE"]}, "dx2J5pWSeLA": {"depth": 8, "recommendations": []}, "Envmqb9GZlY": {"depth": 4, "recommendations": ["ZZninNuU90c"]}, "U-XnWz0WmE8": {"depth": 7, "recommendations": ["gGxdvkoYqrc"]}, "C8vZzP5yvJw": {"depth": 5, "recommendations": ["ZZninNuU90c"]}, "6ZqaizzmO30": {"depth": 4, "recommendations": ["HSMfUlsp4Tw"]}, "lWmyV71Mchw": {"depth": 3, "recommendations": ["6ZqaizzmO30", "jkMLVBHSBvA"]}, "qofdWFv7m0U": {"depth": 2, "recommendations": ["8w0iUOz-ofU", "ZZninNuU90c"]}, "t2ztuFzSiDY": {"depth": 7, "recommendations": ["lRRYLlXHkGs", "b4ifJ1UZCfs"]}, "bah4WFDqKbQ": {"depth": 4, "recommendations": ["C8vZzP5yvJw", "hHhYLJMi7CE"]}, "rQ9X2I3X6UQ": {"depth": 2, "recommendations": ["id5b0PYgvwo", "lWmyV71Mchw"]}, "HSMfUlsp4Tw": {"depth": 5, "recommendations": ["6ZqaizzmO30", "hHhYLJMi7CE"]}, "ZYezDwDURjM": {"depth": 6, "recommendations": ["9812fECnzAo", "WnnzDYk02hk"]}}